pdfmap/__init__.py
pdfmap/pdfmap.py
pdfmap/pdfmaze.py
pdfmap-0.2.1.dist-info/METADATA
pdfmap-0.2.1.dist-info/WHEEL
pdfmap-0.2.1.dist-info/top_level.txt
pdfmap-0.2.1.dist-info/RECORD
